akratiproject/__init__.py
akratiproject/ott_platform.py
akratiproject-0.1.dist-info/License.txt
akratiproject-0.1.dist-info/METADATA
akratiproject-0.1.dist-info/WHEEL
akratiproject-0.1.dist-info/top_level.txt
akratiproject-0.1.dist-info/RECORD
