Metadata-Version: 2.1
Name: akratiproject
Version: 0.1
Summary: This is my project
Author: akrati
Author-email: akrati0021@gmail.com
License: MIT
License-File: License.txt
Requires-Dist: pandas
Requires-Dist: requests
